Workbook

Sheet Summary
A1: Review Master - User Stories Summary
A2: All counts are formulas reading the "All Stories" sheet, so they update when stories, roles, priorities or statuses change.
A4: Stories by role and version
A5: Role | B5: V1 | C5: V2 | D5: V3 | E5: Total
A6: Consumer | B6: =COUNTIFS('All Stories'!$D$5:$D$57,$A6,'All Stories'!$A$5:$A$57,"V1") -> 26 | C6: =COUNTIFS('All Stories'!$D$5:$D$57,$A6,'All Stories'!$A$5:$A$57,"V2") -> 4 | D6: =COUNTIFS('All Stories'!$D$5:$D$57,$A6,'All Stories'!$A$5:$A$57,"V3") -> 3 | E6: =SUM(B6:D6) -> 33
A7: Public Reviewer | B7: =COUNTIFS('All Stories'!$D$5:$D$57,$A7,'All Stories'!$A$5:$A$57,"V1") -> 1 | C7: =COUNTIFS('All Stories'!$D$5:$D$57,$A7,'All Stories'!$A$5:$A$57,"V2") -> 1 | D7: =COUNTIFS('All Stories'!$D$5:$D$57,$A7,'All Stories'!$A$5:$A$57,"V3") -> 0 | E7: =SUM(B7:D7) -> 2
A8: Expert Reviewer | B8: =COUNTIFS('All Stories'!$D$5:$D$57,$A8,'All Stories'!$A$5:$A$57,"V1") -> 1 | C8: =COUNTIFS('All Stories'!$D$5:$D$57,$A8,'All Stories'!$A$5:$A$57,"V2") -> 0 | D8: =COUNTIFS('All Stories'!$D$5:$D$57,$A8,'All Stories'!$A$5:$A$57,"V3") -> 0 | E8: =SUM(B8:D8) -> 1
A9: Admin | B9: =COUNTIFS('All Stories'!$D$5:$D$57,$A9,'All Stories'!$A$5:$A$57,"V1") -> 11 | C9: =COUNTIFS('All Stories'!$D$5:$D$57,$A9,'All Stories'!$A$5:$A$57,"V2") -> 1 | D9: =COUNTIFS('All Stories'!$D$5:$D$57,$A9,'All Stories'!$A$5:$A$57,"V3") -> 1 | E9: =SUM(B9:D9) -> 13
A10: Developer / API Consumer | B10: =COUNTIFS('All Stories'!$D$5:$D$57,$A10,'All Stories'!$A$5:$A$57,"V1") -> 2 | C10: =COUNTIFS('All Stories'!$D$5:$D$57,$A10,'All Stories'!$A$5:$A$57,"V2") -> 1 | D10: =COUNTIFS('All Stories'!$D$5:$D$57,$A10,'All Stories'!$A$5:$A$57,"V3") -> 0 | E10: =SUM(B10:D10) -> 3
A11: Brand / Manufacturer | B11: =COUNTIFS('All Stories'!$D$5:$D$57,$A11,'All Stories'!$A$5:$A$57,"V1") -> 0 | C11: =COUNTIFS('All Stories'!$D$5:$D$57,$A11,'All Stories'!$A$5:$A$57,"V2") -> 1 | D11: =COUNTIFS('All Stories'!$D$5:$D$57,$A11,'All Stories'!$A$5:$A$57,"V3") -> 0 | E11: =SUM(B11:D11) -> 1
A12: Total | B12: =SUM(B6:B11) -> 41 | C12: =SUM(C6:C11) -> 8 | D12: =SUM(D6:D11) -> 4 | E12: =SUM(E6:E11) -> 53
A14: Stories by priority and version
A15: Priority | B15: V1 | C15: V2 | D15: V3 | E15: Total
A16: Must Have | B16: =COUNTIFS('All Stories'!$F$5:$F$57,$A16,'All Stories'!$A$5:$A$57,"V1") -> 26 | C16: =COUNTIFS('All Stories'!$F$5:$F$57,$A16,'All Stories'!$A$5:$A$57,"V2") -> 0 | D16: =COUNTIFS('All Stories'!$F$5:$F$57,$A16,'All Stories'!$A$5:$A$57,"V3") -> 0 | E16: =SUM(B16:D16) -> 26
A17: Should Have | B17: =COUNTIFS('All Stories'!$F$5:$F$57,$A17,'All Stories'!$A$5:$A$57,"V1") -> 15 | C17: =COUNTIFS('All Stories'!$F$5:$F$57,$A17,'All Stories'!$A$5:$A$57,"V2") -> 4 | D17: =COUNTIFS('All Stories'!$F$5:$F$57,$A17,'All Stories'!$A$5:$A$57,"V3") -> 0 | E17: =SUM(B17:D17) -> 19
A18: Could Have | B18: =COUNTIFS('All Stories'!$F$5:$F$57,$A18,'All Stories'!$A$5:$A$57,"V1") -> 0 | C18: =COUNTIFS('All Stories'!$F$5:$F$57,$A18,'All Stories'!$A$5:$A$57,"V2") -> 4 | D18: =COUNTIFS('All Stories'!$F$5:$F$57,$A18,'All Stories'!$A$5:$A$57,"V3") -> 4 | E18: =SUM(B18:D18) -> 8
A19: Total | B19: =SUM(B16:B18) -> 41 | C19: =SUM(C16:C18) -> 8 | D19: =SUM(D16:D18) -> 4 | E19: =SUM(E16:E18) -> 53
A21: Stories by status
A22: Status | B22: Count
A23: Draft | B23: =COUNTIF('All Stories'!$J$5:$J$57,$A23) -> 40
A24: Clarification Required | B24: =COUNTIF('All Stories'!$J$5:$J$57,$A24) -> 13
A25: Ready for Development | B25: =COUNTIF('All Stories'!$J$5:$J$57,$A25) -> 0
A26: In Development | B26: =COUNTIF('All Stories'!$J$5:$J$57,$A26) -> 0
A27: Ready for QA | B27: =COUNTIF('All Stories'!$J$5:$J$57,$A27) -> 0
A28: Done | B28: =COUNTIF('All Stories'!$J$5:$J$57,$A28) -> 0
A29: Blocked | B29: =COUNTIF('All Stories'!$J$5:$J$57,$A29) -> 0
A30: Total | B30: =SUM(B23:B29) -> 53
A32: Check
A33: Stories listed (All Stories) | B33: =COUNTA('All Stories'!$B$5:$B$57) -> 53
A34: Role table matches list? | B34: =IF(E12=B33,"OK","MISMATCH") -> OK
A36: Notes
A37: Priority order: Must Have (V1 core) > Should Have (V1 desirable / V2) > Could Have (V2 pilot / V3 and long-term).
A38: Roles are grouped in this order: Consumer, Public Reviewer, Expert Reviewer, Admin, Developer / API Consumer, Brand / Manufacturer.
A39: Sheets V1 MVP, V2 Assistant and V3 Long-term show role banners; "All Stories" is a flat list with filters.
A40: Status values follow the template: Draft / Clarification Required / Ready for Development / In Development / Ready for QA / Done / Blocked.
A41: Source: Review Master Master Project Capsule v1.0 (2026-10-01). Story IDs match the Word document Review_Master_User_Stories.docx.

Sheet V1 MVP
A1: Review Master - User Stories - V1 - Controlled MVP (one marketplace, 3-5 categories, extension + responsive web)
A2: Grouped by role, ordered Must Have > Should Have > Could Have within each role. Use the "All Stories" sheet for filtering.
A4: Version | B4: Story ID | C4: Title | D4: Role | E4: Module | F4: Priority | G4: User Story (Goal) | H4: Acceptance Criteria | I4: Detailed Test Conditions | J4: Status
A5: ROLE: CONSUMER
A6: V1 | B6: US-001 | C6: Detect product on supported marketplace page | D6: Consumer | E6: Extension | F6: Must Have | G6: As a Consumer, I want the browser extension to recognise the product and exact variant on a supported marketplace page, so that I can see Review Master insights without searching manually. | H6: • Extension activates only on the single V1-supported marketplace through its marketplace adapter. • Only permitted page attributes are extracted; no private cookies, credentials, or browsing history are collected. • Panel shows product name and exact variant once identified. • Unsupported pages show a clear "not supported" message instead of wrong data. • Extension requests minimum host permissions. | I6: • Positive: open a supported product page; panel loads with product name and variant. • Negative: open an unsupported site; "not supported" message, no API call with page data. • Negative: Review Master API is down; friendly error with retry, no crash. • Edge: listing has no model number; user is told identity is ambiguous. • Security: inspect the manifest; permissions limited to the supported host; no cookie access. | J6: Clarification Required
A7: V1 | B7: US-002 | C7: Resolve canonical product and variant | D7: Consumer | E7: Product | F7: Must Have | G7: As a Consumer, I want a marketplace listing mapped to the exact canonical product and variant, so that the evaluation I see applies to the thing I am actually considering. | H7: • Listing maps to product_id and variant_id; identity never depends on a marketplace URL. • Matching order: verified marketplace ID mapping, model number, generation, exact configuration, normalized attributes, human review for ambiguous cases. • AI may assist extraction but never silently merges products. • Ambiguous matches are flagged for admin review and shown to the user as unconfirmed. | I7: • Positive: same model with 16 GB/512 GB vs 16 GB/1 TB resolves to two different variants. • Positive: same listing opened via two different URLs resolves to one product. • Negative: LLM-extracted model name conflicts with the verified ID mapping; verified mapping wins. • Edge: missing model number or ambiguous listing goes to the review queue, not auto-merged. • Edge: new generation with a similar name is not merged with the older generation. | J7: Draft
A8: V1 | B8: US-003 | C8: Correct product identification | D8: Consumer | E8: Product | F8: Must Have | G8: As a Consumer, I want to correct a wrong product or variant match, so that I stay in control of what is being evaluated. | H8: • User can flag an identification as wrong and optionally pick the correct variant. • The correction is stored and sent to the admin mapping queue; it does not directly alter the canonical mapping for other users. • The user sees the corrected product for their session. • Correction rate is recorded as a KPI input. | I8: • Positive: user selects the correct variant and the evaluation view refreshes. • Negative: anonymous user attempts to alter the global mapping; request rejected. • Edge: many users submit conflicting corrections; all are queued, none auto-applied. • Verify the correction event appears in the audit log. | J8: Draft
A9: V1 | B9: US-004 | C9: View normalized specifications | D9: Consumer | E9: Product | F9: Must Have | G9: As a Consumer, I want product specifications shown in a normalized, consistent form, so that I can understand and compare them across listings. | H9: • Specs are grouped according to the category schema (Smartphone, Laptop, External SSD). • Units are normalized (for example GB/TB, MB/s). • Each spec shows its source and freshness. • Missing specs are displayed as "not available", never as zero. | I9: • Positive: 1 TB and 1000 GB inputs both display as the same normalized capacity. • Negative: spec absent in source; shown as "not available" and not scored as 0. • Edge: conflicting specs from manufacturer and marketplace; conflict is shown with both sources. • Edge: unrecognized unit; value flagged for review rather than guessed. | J9: Draft
A10: V1 | B10: US-005 | C10: Search products on the website | D10: Consumer | E10: Product | F10: Must Have | G10: As a Consumer, I want to search for products by name, model, or category on the website, so that I can evaluate items without being on a marketplace page. | H10: • Search returns canonical products (not raw marketplace listings). • Results can be filtered by category. • Each result links to the product detail page within about 3 clicks of landing. • No-result searches show helpful guidance. | I10: • Positive: search by exact model name returns the matching product first. • Positive: search by category returns only products in that category. • Negative: empty or whitespace query; validation message. • Edge: misspelled model name; relevant suggestions or "no match" message. | J10: Draft
A11: V1 | B11: US-006 | C11: View product page with separated trust outputs | D11: Consumer | E11: Product | F11: Must Have | G11: As a Consumer, I want the product page to show the Review Master evaluation, community experience, and expert assessment separately, so that I understand where each signal comes from. | H11: • Three distinct sections: Review Master evaluation, Community experience, Expert assessment. • The three are never blended into one number. • External marketplace ratings appear only where permitted and are labelled as external information. • Product quality, price, and sentiment remain visibly separate signals. | I11: • Positive: product with all three data types shows three separate sections. • Positive: product with no expert assessment shows "no expert assessment yet". • Negative: verify no combined score is computed from community and expert data. • Edge: marketplace rating unavailable or not permitted; section hidden, not zero. | J11: Draft
A12: V1 | B12: US-008 | C12: Deterministic category-based evaluation | D12: Consumer | E12: Evaluation | F12: Must Have | G12: As a Consumer, I want products scored by a deterministic, category-specific model, so that scores are consistent, explainable, and not invented by an AI. | H12: • Engine inputs: canonical variant, validated specs, eligible evidence, category evaluation model. • Outputs: parameter results, overall score, confidence, evidence references, limitations, model version. • V1 models exist for Smartphones, Laptops, and External SSDs. • LLM is never the scoring authority; missing data never silently becomes zero. • Extension, web, and API show the same score (no interface computes its own). | I12: • Positive: same inputs run twice give identical scores and the same model version. • Positive: score from extension, web, and API match for one variant. • Negative: critical evidence missing; result is Limited or Insufficient, not a low score. • Edge: conflicting evidence from two sources is handled by the documented rule and flagged. • Edge: unit normalization (TB vs GB, MB/s vs GB/s) produces correct parameter scores. | J12: Clarification Required
A13: V1 | B13: US-009 | C13: View Review Master score and parameter scores | D13: Consumer | E13: Evaluation | F13: Must Have | G13: As a Consumer, I want to see the overall score and each parameter score, so that I know why a product scored the way it did. | H13: • Overall score and category parameter scores are displayed (for example performance, battery, camera for smartphones). • Model name and version are shown. • Score drivers and limitations are visible. • Common cached evaluation loads in about 2 seconds or less. | I13: • Positive: smartphone shows all smartphone parameters. • Positive: cached evaluation responds within the 2-second target under normal load. • Negative: product without a published evaluation shows "not yet evaluated". • Edge: product evaluated on an old model version displays that version. | J13: Draft
A14: V1 | B14: US-010 | C14: View confidence level separate from score | D14: Consumer | E14: Evaluation | F14: Must Have | G14: As a Consumer, I want to see how confident Review Master is in an evaluation, so that I do not over-trust a high score based on thin evidence. | H14: • Confidence is shown as High confidence, Limited confidence, or Insufficient evidence. • Confidence considers evidence coverage, source quality, verification, freshness, consistency, and critical missing parameters. • Confidence is displayed separately from the score. • Reasons for reduced confidence are listed. | I14: • Positive: strong score with little evidence shows Limited confidence. • Positive: fully evidenced, fresh, consistent data shows High confidence. • Negative: critical parameter missing; Insufficient evidence is shown. • Edge: evidence becomes stale; confidence downgrades after re-evaluation. | J14: Clarification Required
A15: V1 | B15: US-011 | C15: Inspect evidence and its provenance | D15: Consumer | E15: Evaluation | F15: Must Have | G15: As a Consumer, I want to open the evidence behind a parameter score, so that I can verify where the information came from. | H15: • Each evidence item shows source, source type, timestamp, freshness, verification state, methodology (where relevant), and document reference. • Evidence types are labelled: independently tested, expert-tested, manufacturer-published, marketplace-provided, community-reported, other authorized. • A manufacturer claim is never presented as an independent test. • A community complaint is never presented as a laboratory fact. | I15: • Positive: click a parameter; linked evidence opens with all provenance fields. • Negative: manufacturer spec sheet is not shown with the "independently tested" label. • Edge: evidence document later withdrawn; item marked as such and evaluation flagged for review. • Security: private evidence is hidden from users without permission. | J15: Draft
A16: V1 | B16: US-015 | C16: View community insights | D16: Consumer | E16: Community | F16: Must Have | G16: As a Consumer, I want a summary of community feedback, so that I can see recurring issues and positive experiences without reading every review. | H16: • Shows sentiment, recurring issues, positive experiences, and usage context. • Shown separately from the objective evaluation. • AI summaries are labelled and traceable to underlying feedback. • Feedback history is retained. | I16: • Positive: product with many reviews shows top recurring issues. • Negative: product with too few reviews shows a "not enough feedback" state. • Edge: contradictory feedback is shown as mixed, not averaged away. • Verify community data does not change the deterministic evaluation score. | J16: Draft
A17: V1 | B17: US-018 | C17: Compare products side by side | D17: Consumer | E17: Compare | F17: Must Have | G17: As a Consumer, I want to compare two or more products parameter by parameter, so that I can see the trade-offs and pick the right one. | H17: • Comparison shows score, parameter scores, confidence, key specs, and offers for each product. • Quality, price, and confidence are shown as separate signals. • Products are compared on the same category model; cross-category compare is blocked with an explanation. • Common compare actions need about 3 clicks or fewer. | I17: • Positive: compare two laptops; all shared parameters are aligned. • Negative: compare a smartphone with a laptop; clear "different categories" message. • Edge: one product has Insufficient evidence; shown clearly, not ranked as zero. • Edge: more products than the supported maximum; limit message. | J17: Draft
... A31: V1 | B31: US-028 | C31: Control notification types | D31: Consumer | E31: Notification | F31: Should Have | G31: As a Consumer, I want to choose which notifications I receive, so that I am not overloaded. | H31: • User can enable or disable price alerts, evaluation changes, low-confidence alerts, and stale-data reminders per channel. • Defaults avoid excessive notifications. • Delivery is processed asynchronously. | I31: • Positive: disable email alerts; no emails are sent. • Negative: unauthenticated request to change settings is rejected. • Edge: multiple events in a short window are grouped or throttled. | J31: Draft
A32: ROLE: PUBLIC REVIEWER
A33: V1 | B33: US-014 | C33: Submit structured feedback | D33: Public Reviewer | E33: Community | F33: Must Have | G33: As a Public Reviewer, I want to submit structured feedback about a specific product variant, so that my real experience helps other consumers. | H33: • Reviewer must be logged in; feedback is tied to the exact variant. • Structured fields are used (for example ratings by parameter, usage context, issues, positives). • New feedback enters a moderation state before publication. • Reviewer can edit or delete their own feedback. | I33: • Positive: valid feedback is saved as pending and appears after moderation. • Negative: guest submission blocked; empty required fields rejected. • Edge: reviewer submits feedback for a variant different from the one they own; stored against the chosen variant and not merged. • Security: reviewer cannot edit someone else's feedback. | J33: Draft
A34: ROLE: EXPERT REVIEWER
A35: V1 | B35: US-031 | C35: Submit expert assessment with proof | D35: Expert Reviewer | E35: Expert | F35: Should Have | G35: As an Expert Reviewer, I want to inspect evidence, run tests, upload proof, and submit parameter-level findings, so that my assessment is credible and traceable. | H35: • Assessment includes product/variant, expert identity, qualifications, conflict declaration, methodology, test conditions, evidence, parameter findings, limitations, date, and approval state. • Experts can only see and act on their assigned cases. • Experts cannot directly change a published score and cannot approve their own assessment. • Uploaded files are treated as untrusted input. | I35: • Positive: complete assessment is submitted into quality review. • Negative: expert attempts to approve their own assessment; blocked. • Negative: expert opens an unassigned case; access denied. • Security: malicious file upload is rejected or quarantined. | J35: Clarification Required
A36: ROLE: ADMIN
A37: V1 | B37: US-017 | C37: Moderate community feedback | D37: Admin | E37: Community | F37: Must Have | G37: As an Admin, I want to approve, reject, or flag feedback, so that published community content is trustworthy. | H37: • Moderation queue lists pending and flagged feedback with anomaly signals. • Each decision records moderator, time, and reason. • Rejected feedback is retained for audit, not hard-deleted. • A feedback.moderated event is emitted. | I37: • Positive: approve feedback; it becomes visible on the product page. • Negative: non-admin cannot access the moderation queue. • Edge: reviewer edits feedback while it is under review; moderator sees the latest version and the history. • Verify the audit log entry exists for each decision. | J37: Draft
A38: V1 | B38: US-033 | C38: Manage users, roles, and permissions | D38: Admin | E38: Admin | F38: Must Have | G38: As an Admin, I want to manage users and role-based permissions, so that each person has only the access they need. | H38: • Roles supported: Consumer, Public Reviewer, Expert Reviewer, Admin, Developer/API Consumer. • Least-privilege RBAC is enforced on every API. • Role changes are audit logged. • Users cannot escalate their own role. | I38: • Positive: admin grants Expert role; expert portal becomes available. • Negative: Consumer calls an admin API; 403 returned. • Security: modified token or request cannot escalate role. • Verify role changes appear in the audit log. | J38: Draft
A39: V1 | B39: US-034 | C39: Manage categories and versioned evaluation models | D39: Admin | E39: Admin | F39: Must Have | G39: As an Admin, I want to configure category evaluation models with versions, so that scoring rules are controlled and historical results stay auditable. | H39: • A model defines parameters, definitions, weights, normalization rules, evidence requirements, confidence policy, version, and status. • Publishing a model needs explicit approval. • Final parameters and weights are validated before publication; V1 example weights are not production values. • Existing evaluations keep the model version used. | I39: • Positive: create Smartphone v1 as draft, validate, publish. • Negative: edit a published model in place; blocked, new version required. • Edge: new version published; old evaluations remain linked to the old version. • Verify publication is audit logged. | J39: Clarification Required
A40: V1 | B40: US-035 | C40: Manage product mappings and ambiguous matches | D40: Admin | E40: Admin | F40: Must Have | G40: As an Admin, I want to review ambiguous or user-corrected product matches, so that canonical identities stay accurate. | H40: • Queue lists ambiguous matches and user corrections with supporting attributes. • Admin can confirm, change, or split a mapping. • Mapping changes are versioned and audit logged. | I40: • Positive: confirm a mapping; future listings resolve automatically. • Negative: non-admin cannot access the queue. • Edge: split an incorrectly merged product; existing evaluations are reassigned or re-evaluated correctly. | J40: Draft
A41: V1 | B41: US-036 | C41: Protect and manage evidence | D41: Admin | E41: Admin | F41: Must Have | G41: As an Admin, I want evidence stored securely with provenance and versioning, so that it can be trusted and audited. | H41: • Uploaded evidence is treated as untrusted (type and size validation, malware scanning). • Private evidence is accessible only to authorized roles. • Evidence changes create new versions; nothing is silently overwritten. • Evidence metadata includes source, source type, timestamp, verification state. | I41: • Positive: valid report uploaded and stored with metadata. • Negative: executable disguised as a PDF is rejected. • Security: user without permission cannot fetch the private evidence URL. • Edge: replacing an evidence file keeps the prior version. | J41: Draft
A42: V1 | B42: US-037 | C42: Audit log of material changes | D42: Admin | E42: Admin | F42: Must Have | G42: As an Admin, I want every material change recorded in an audit log, so that decisions can be traced and reviewed. | H42: • Logs capture actor, action, object, timestamp, and before/after values. • Covers role changes, model publication, mapping changes, moderation, expert decisions, integration changes, and API key actions. • Audit records cannot be edited or deleted through the UI. | I42: • Positive: publish a model; audit entry appears with actor and version. • Negative: attempt to delete an audit entry; denied. • Edge: failed action (permission denied) is also recorded. | J42: Draft
A43: V1 | B43: US-039 | C43: Keep commercial relationships out of scoring | D43: Admin | E43: Admin | F43: Must Have | G43: As an Admin, I want a guarantee that affiliate, brand, or partner relationships cannot alter independent scores, so that Review Master stays trustworthy. | H43: • No API or role allows a commercial customer to edit scores, evidence verdicts, or expert findings. • Commercial relationships are disclosed where relevant. • Affiliate revenue and price are separate from quality in data and UI. | I43: • Negative: brand or API-key user attempts to change a score; denied. • Negative: affiliate flag has no influence on the evaluation output. • Verify disclosure labels appear on sponsored or affiliated links. | J43: Draft
A44: V1 | B44: US-029 | C44: Create investigation case from potential issue | D44: Admin | E44: Expert | F44: Should Have | G44: As an Admin, I want to triage a potential review or product-quality issue into an investigation case, so that it can be examined by an expert. | H44: • Admin can open a case from flagged feedback, anomaly signals, or a user report. • Case records product/variant, reason, evidence references, and status. • Admin cannot replace a marketplace rating with an arbitrary rating. • Case actions are audit logged. | I44: • Positive: flagged product becomes a case with linked evidence. • Negative: admin tries to directly set a score from a case; blocked. • Edge: duplicate case for the same issue; user warned and cases can be linked. | J44: Clarification Required
A45: V1 | B45: US-030 | C45: Assign expert with conflict-of-interest check | D45: Admin | E45: Expert | F45: Should Have | G45: As an Admin, I want to assign a case to a qualified expert after a conflict-of-interest check, so that the assessment is independent. | H45: • Expert declares conflicts before accepting. • Assignment is blocked if a conflict is declared or detected. • Commercial relationships are disclosed on the case. • Assignment, acceptance, and decline are logged. | I45: • Positive: expert with no conflict is assigned and accepts. • Negative: expert with a declared brand relationship is blocked. • Edge: expert declines; case returns to the pool. | J45: Clarification Required
A46: V1 | B46: US-032 | C46: Quality review and publish expert assessment | D46: Admin | E46: Expert | F46: Should Have | G46: As an Admin, I want to review and approve or reject expert assessments before publication, so that only evidence-backed findings affect the platform. | H46: • Reviewer can approve, reject, or return an assessment with comments. • Published assessment is shown separately from the Review Master evaluation and community feedback. • The evaluation is updated only if the evidence supports it, via the normal versioned engine. • Historical evidence is never silently overwritten. | I46: • Positive: approved assessment appears on the product page and triggers re-evaluation. • Negative: rejected assessment is never publicly visible. • Edge: new assessment contradicts an older one; both are retained with dates. | J46: Clarification Required
A47: V1 | B47: US-038 | C47: Monitor integrations and system health | D47: Admin | E47: Admin | F47: Should Have | G47: As an Admin, I want to see the status and freshness of marketplace integrations and background jobs, so that I can react to failures. | H47: • Shows adapter status, last sync, freshness, and errors. • Failures raise integration.error events. • Ingestion, price refresh, and evaluation jobs show success and failure counts. | I47: • Positive: healthy adapter shows green status and last sync time. • Negative: simulate adapter failure; error shown and event emitted. • Edge: repeated failures are retried with backoff and not duplicated. | J47: Draft
A48: ROLE: DEVELOPER / API CONSUMER
A49: V1 | B49: US-040 | C49: Access versioned secure APIs | D49: Developer / API Consumer | E49: API | F49: Must Have | G49: As a Developer/API Consumer, I want to call versioned, authenticated APIs for products, evaluations, comparisons, and recommendations, so that I can build on Review Master reliably. | H49: • Endpoints are versioned under /api/v1 (products, evaluations, comparisons, recommendations, offers, prices, and others). • Authentication via API keys (OAuth where applicable) with permission scopes. • Rate limiting and idempotency are supported. • Responses carry confidence, model version, and evidence references. | I49: • Positive: valid key retrieves an evaluation by product ID. • Negative: missing or invalid key returns 401; out-of-scope key returns 403. • Negative: exceeding the rate limit returns 429. • Edge: repeated POST with the same idempotency key creates one record. | J49: Draft
A50: V1 | B50: US-041 | C50: Receive signed webhooks for events | D50: Developer / API Consumer | E50: API | F50: Should Have | G50: As a Developer/API Consumer, I want signed webhook events (for example product.evaluated, price.changed), so that my system stays in sync. | H50: • Events delivered to registered endpoints with a verifiable signature. • Failed deliveries are retried with backoff. • Event payloads follow documented schemas. | I50: • Positive: evaluation update sends product.evaluated with a valid signature. • Negative: tampered payload fails signature verification. • Edge: endpoint down; retries then marked failed and surfaced to admin. | J50: Clarification Required

Sheet V2 Assistant
A1: Review Master - User Stories - V2 - Active shopping assistant
A2: Grouped by role, ordered Must Have > Should Have > Could Have within each role. Use the "All Stories" sheet for filtering.
A4: Version | B4: Story ID | C4: Title | D4: Role | E4: Module | F4: Priority | G4: User Story (Goal) | H4: Acceptance Criteria | I4: Detailed Test Conditions | J4: Status
A5: ROLE: CONSUMER
A6: V2 | B6: US-042 | C6: Conversational product Q&A | D6: Consumer | E6: Chat / AI | F6: Should Have | G6: As a Consumer, I want to ask questions about products in natural language, so that I can get grounded answers without navigating the UI. | H6: • Chatbot uses explicit backend tools (search_products, get_evaluation, compare_products, get_offers, and similar), not direct database access. • Answers are grounded in structured tool results and checked for permission and evidence. • The chatbot never invents specs, scores, evidence, prices, availability, or expert findings. • Consequential actions (save product, create alert) require user confirmation. | I6: • Positive: "Is this SSD good for 4K editing?" returns an answer citing the evaluation. • Negative: question about an unsupported product; chatbot says it lacks data. • Security: prompt injection cannot trigger tools outside the user's permissions. • Edge: tool returns Insufficient evidence; answer reflects uncertainty. | J6: Draft
A7: V2 | B7: US-043 | C7: Buy / track / wait guidance | D7: Consumer | E7: Offer & Price | F7: Should Have | G7: As a Consumer, I want guidance on whether to buy now, track, or wait, so that I can time my purchase. | H7: • Guidance considers current price, history, data coverage, urgency, budget, availability, and verified sale information. • Language never claims a future price with certainty without reliable evidence. • Advanced forecasting is excluded until V3. | I7: • Positive: strong price drop with solid history suggests "buy now" with reasons. • Negative: sparse data produces a cautious "track" message. • Edge: user urgency is high; guidance reflects it. | J7: Draft
A8: V2 | B8: US-045 | C8: Mobile app: share URL and compare | D8: Consumer | E8: Mobile | F8: Could Have | G8: As a Consumer, I want to share a product URL to the Review Master mobile app, so that I can see evaluations on my phone. | H8: • Mobile reuses the same backend APIs and scores. • The app does not read private data from other apps. • Supports search, compare, saved products, chatbot, notifications, and price alerts. | I8: • Positive: share a marketplace link; the product evaluation opens. • Negative: link to an unsupported site gives a clear message. • Verify no access to other apps' private data is requested. | J8: Draft
A9: V2 | B9: US-049 | C9: Retrieve answers from approved documents (RAG) | D9: Consumer | E9: Chat / AI | F9: Could Have | G9: As a Consumer, I want answers to draw on approved manuals, test reports, and methodology documents, so that responses are well-informed. | H9: • Retrieval covers only approved expert reports, manuals, manufacturer documents, test reports, and methodology. • Retrieved text is not treated as verified just because it was retrieved. • Retrieval never affects the deterministic score. | I9: • Positive: question about a documented spec returns an answer with its source. • Negative: unapproved document is never retrieved. • Edge: conflicting documents are both shown with their source types. | J9: Draft
A10: ROLE: PUBLIC REVIEWER
A11: V2 | B11: US-046 | C11: Post-purchase feedback with purchase verification | D11: Public Reviewer | E11: Community | F11: Could Have | G11: As a Public Reviewer, I want to optionally verify my purchase, so that my feedback is marked as verified. | H11: • Verification methods: authorized affiliate links, authorized marketplace APIs, user-shared links, optional receipt/invoice. • Affiliate click, attributed conversion, and verified purchase are separate states. • A click is never treated as a purchase. | I11: • Positive: upload receipt; feedback shows "verified purchase". • Negative: click-through only; no verified label. • Security: receipt files are scanned, access is private, and retention rules apply. | J11: Draft
A12: ROLE: ADMIN
A13: V2 | B13: US-044 | C13: Add an authorized marketplace adapter | D13: Admin | E13: Admin | F13: Should Have | G13: As an Admin, I want to onboard another marketplace through the adapter interface, so that Review Master expands without changing the evaluation engine. | H13: • New adapter implements the standard capabilities (identify listing, extract permitted attributes, normalize, identify variant, return offers, source metadata, freshness, status). • No evaluation code depends on a marketplace-specific implementation. • Only official APIs, licensed feeds, authorized providers, or permitted extraction are used. | I13: • Positive: add second adapter; evaluation output for the same canonical product is unchanged. • Negative: adapter attempting restricted data collection fails compliance review. • Edge: adapter outage does not affect other adapters. | J13: Draft
A14: ROLE: DEVELOPER / API CONSUMER
A15: V2 | B15: US-048 | C15: Product-intelligence commercial API | D15: Developer / API Consumer | E15: API | F15: Should Have | G15: As a Developer/API Consumer, I want a commercial API for identity, evaluation, evidence metadata, comparisons, and recommendations, so that I can integrate Review Master into my product. | H15: • Subscription and key management for B2B customers. • Tenant isolation between customers. • Usage metering and rate limiting. | I15: • Positive: customer A key returns data for its plan only. • Security: customer A cannot access customer B's data. • Edge: plan limit exceeded; request blocked with a clear error. | J15: Draft
A16: ROLE: BRAND / MANUFACTURER
A17: V2 | B17: US-047 | C17: Brand profile and evidence submission | D17: Brand / Manufacturer | E17: Admin | F17: Could Have | G17: As a Brand representative, I want to claim our profile, submit specifications and evidence, and respond to documented issues, so that our products are represented accurately. | H17: • Brand claims are labelled "manufacturer-published" and never as independent tests. • Brand can request independent testing as a paid service. • Brand cannot modify scores or buy a better evaluation. | I17: • Positive: brand uploads spec sheet; evidence is labelled as manufacturer-published. • Negative: brand attempts to edit a score; denied. • Verify commercial relationship is disclosed on the product page. | J17: Clarification Required

Sheet V3 Long-term
A1: Review Master - User Stories - V3 - Universal intelligence layer and CEO long-term vision
A2: Grouped by role, ordered Must Have > Should Have > Could Have within each role. Use the "All Stories" sheet for filtering.
A4: Version | B4: Story ID | C4: Title | D4: Role | E4: Module | F4: Priority | G4: User Story (Goal) | H4: Acceptance Criteria | I4: Detailed Test Conditions | J4: Status
A5: ROLE: CONSUMER
A6: V3 | B6: US-050 | C6: Context-aware questions via context graph | D6: Consumer | E6: Chat / AI | F6: Could Have | G6: As a Consumer, I want to ask context-aware questions that link my preferences, products, offers, and evidence, so that I do not have to assemble information myself. | H6: • Graph links preferences, products, categories, specs, offers, evaluations, evidence, feedback, comparisons, recommendations, and decisions. • Answers remain grounded and permission-checked. • Preference learning has user controls. | I6: • Positive: "Which of my saved laptops best fits my battery priority?" returns a grounded answer. • Negative: user cannot query another user's graph. • Verify the user can reset learned preferences. | J6: Draft
A7: V3 | B7: US-051 | C7: Predictive price and quality-change detection | D7: Consumer | E7: Offer & Price | F7: Could Have | G7: As a Consumer, I want warnings about likely price changes and shifts in product quality or confidence, so that I can act early. | H7: • Predictions are labelled as estimates with their evidence basis. • Quality and confidence change detection is based on new evidence, not speculation. • Controlled monitoring respects notification limits. | I7: • Positive: new durability evidence triggers a quality-change notice. • Negative: weak data produces no strong prediction. • Edge: conflicting signals are surfaced as uncertain. | J7: Draft
A8: V3 | B8: US-052 | C8: Household / multi-user shopping | D8: Consumer | E8: Recommendation | F8: Could Have | G8: As a Consumer, I want to shop with household members, so that we can share lists and requirements. | H8: • Users can form a household with shared saved products and requirements. • Personal preferences and private data stay private unless shared. • Roles within a household are controlled. | I8: • Positive: member adds a product to the shared list; the other member sees it. • Security: private preferences are not exposed to other members. • Edge: member leaves the household; shared access is removed. | J8: Draft
A9: ROLE: ADMIN
A10: V3 | B10: US-053 | C10: Add a new domain evaluation model (restaurants, hotels, services) | D10: Admin | E10: Admin | F10: Could Have | G10: As an Admin, I want to add evaluation models for new domains (for example Restaurant v1, Hotel v1) on the shared entity platform, so that Review Master expands beyond products. | H10: • A new domain reuses shared identity, evidence, feedback, expert, confidence, comparison, recommendation, notification, and AI infrastructure. • Only domain parameters, normalization, evidence requirements, scoring rules, and recommendation constraints are new. • No redesign of the core platform is required. | I10: • Positive: configure a Restaurant v1 model; an entity can be evaluated end to end. • Verify product categories are unaffected by the new domain. • Edge: domain-specific evidence requirement differs; engine enforces it. | J10: Clarification Required

Sheet All Stories
A1: Review Master - All User Stories (filterable)
A2: Sorted by Version, then Role, then Priority. Use the header filters to slice any other way.
A4: Version | B4: Story ID | C4: Title | D4: Role | E4: Module | F4: Priority | G4: User Story (Goal) | H4: Acceptance Criteria | I4: Detailed Test Conditions | J4: Status
A5: V1 | B5: US-001 | C5: Detect product on supported marketplace page | D5: Consumer | E5: Extension | F5: Must Have | G5: As a Consumer, I want the browser extension to recognise the product and exact variant on a supported marketplace page, so that I can see Review Master insights without searching manually. | H5: • Extension activates only on the single V1-supported marketplace through its marketplace adapter. • Only permitted page attributes are extracted; no private cookies, credentials, or browsing history are collected. • Panel shows product name and exact variant once identified. • Unsupported pages show a clear "not supported" message instead of wrong data. • Extension requests minimum host permissions. | I5: • Positive: open a supported product page; panel loads with product name and variant. • Negative: open an unsupported site; "not supported" message, no API call with page data. • Negative: Review Master API is down; friendly error with retry, no crash. • Edge: listing has no model number; user is told identity is ambiguous. • Security: inspect the manifest; permissions limited to the supported host; no cookie access. | J5: Clarification Required
A6: V1 | B6: US-002 | C6: Resolve canonical product and variant | D6: Consumer | E6: Product | F6: Must Have | G6: As a Consumer, I want a marketplace listing mapped to the exact canonical product and variant, so that the evaluation I see applies to the thing I am actually considering. | H6: • Listing maps to product_id and variant_id; identity never depends on a marketplace URL. • Matching order: verified marketplace ID mapping, model number, generation, exact configuration, normalized attributes, human review for ambiguous cases. • AI may assist extraction but never silently merges products. • Ambiguous matches are flagged for admin review and shown to the user as unconfirmed. | I6: • Positive: same model with 16 GB/512 GB vs 16 GB/1 TB resolves to two different variants. • Positive: same listing opened via two different URLs resolves to one product. • Negative: LLM-extracted model name conflicts with the verified ID mapping; verified mapping wins. • Edge: missing model number or ambiguous listing goes to the review queue, not auto-merged. • Edge: new generation with a similar name is not merged with the older generation. | J6: Draft
A7: V1 | B7: US-003 | C7: Correct product identification | D7: Consumer | E7: Product | F7: Must Have | G7: As a Consumer, I want to correct a wrong product or variant match, so that I stay in control of what is being evaluated. | H7: • User can flag an identification as wrong and optionally pick the correct variant. • The correction is stored and sent to the admin mapping queue; it does not directly alter the canonical mapping for other users. • The user sees the corrected product for their session. • Correction rate is recorded as a KPI input. | I7: • Positive: user selects the correct variant and the evaluation view refreshes. • Negative: anonymous user attempts to alter the global mapping; request rejected. • Edge: many users submit conflicting corrections; all are queued, none auto-applied. • Verify the correction event appears in the audit log. | J7: Draft
A8: V1 | B8: US-004 | C8: View normalized specifications | D8: Consumer | E8: Product | F8: Must Have | G8: As a Consumer, I want product specifications shown in a normalized, consistent form, so that I can understand and compare them across listings. | H8: • Specs are grouped according to the category schema (Smartphone, Laptop, External SSD). • Units are normalized (for example GB/TB, MB/s). • Each spec shows its source and freshness. • Missing specs are displayed as "not available", never as zero. | I8: • Positive: 1 TB and 1000 GB inputs both display as the same normalized capacity. • Negative: spec absent in source; shown as "not available" and not scored as 0. • Edge: conflicting specs from manufacturer and marketplace; conflict is shown with both sources. • Edge: unrecognized unit; value flagged for review rather than guessed. | J8: Draft
A9: V1 | B9: US-005 | C9: Search products on the website | D9: Consumer | E9: Product | F9: Must Have | G9: As a Consumer, I want to search for products by name, model, or category on the website, so that I can evaluate items without being on a marketplace page. | H9: • Search returns canonical products (not raw marketplace listings). • Results can be filtered by category. • Each result links to the product detail page within about 3 clicks of landing. • No-result searches show helpful guidance. | I9: • Positive: search by exact model name returns the matching product first. • Positive: search by category returns only products in that category. • Negative: empty or whitespace query; validation message. • Edge: misspelled model name; relevant suggestions or "no match" message. | J9: Draft
A10: V1 | B10: US-006 | C10: View product page with separated trust outputs | D10: Consumer | E10: Product | F10: Must Have | G10: As a Consumer, I want the product page to show the Review Master evaluation, community experience, and expert assessment separately, so that I understand where each signal comes from. | H10: • Three distinct sections: Review Master evaluation, Community experience, Expert assessment. • The three are never blended into one number. • External marketplace ratings appear only where permitted and are labelled as external information. • Product quality, price, and sentiment remain visibly separate signals. | I10: • Positive: product with all three data types shows three separate sections. • Positive: product with no expert assessment shows "no expert assessment yet". • Negative: verify no combined score is computed from community and expert data. • Edge: marketplace rating unavailable or not permitted; section hidden, not zero. | J10: Draft
A11: V1 | B11: US-008 | C11: Deterministic category-based evaluation | D11: Consumer | E11: Evaluation | F11: Must Have | G11: As a Consumer, I want products scored by a deterministic, category-specific model, so that scores are consistent, explainable, and not invented by an AI. | H11: • Engine inputs: canonical variant, validated specs, eligible evidence, category evaluation model. • Outputs: parameter results, overall score, confidence, evidence references, limitations, model version. • V1 models exist for Smartphones, Laptops, and External SSDs. • LLM is never the scoring authority; missing data never silently becomes zero. • Extension, web, and API show the same score (no interface computes its own). | I11: • Positive: same inputs run twice give identical scores and the same model version. • Positive: score from extension, web, and API match for one variant. • Negative: critical evidence missing; result is Limited or Insufficient, not a low score. • Edge: conflicting evidence from two sources is handled by the documented rule and flagged. • Edge: unit normalization (TB vs GB, MB/s vs GB/s) produces correct parameter scores. | J11: Clarification Required
A12: V1 | B12: US-009 | C12: View Review Master score and parameter scores | D12: Consumer | E12: Evaluation | F12: Must Have | G12: As a Consumer, I want to see the overall score and each parameter score, so that I know why a product scored the way it did. | H12: • Overall score and category parameter scores are displayed (for example performance, battery, camera for smartphones). • Model name and version are shown. • Score drivers and limitations are visible. • Common cached evaluation loads in about 2 seconds or less. | I12: • Positive: smartphone shows all smartphone parameters. • Positive: cached evaluation responds within the 2-second target under normal load. • Negative: product without a published evaluation shows "not yet evaluated". • Edge: product evaluated on an old model version displays that version. | J12: Draft
A13: V1 | B13: US-010 | C13: View confidence level separate from score | D13: Consumer | E13: Evaluation | F13: Must Have | G13: As a Consumer, I want to see how confident Review Master is in an evaluation, so that I do not over-trust a high score based on thin evidence. | H13: • Confidence is shown as High confidence, Limited confidence, or Insufficient evidence. • Confidence considers evidence coverage, source quality, verification, freshness, consistency, and critical missing parameters. • Confidence is displayed separately from the score. • Reasons for reduced confidence are listed. | I13: • Positive: strong score with little evidence shows Limited confidence. • Positive: fully evidenced, fresh, consistent data shows High confidence. • Negative: critical parameter missing; Insufficient evidence is shown. • Edge: evidence becomes stale; confidence downgrades after re-evaluation. | J13: Clarification Required
A14: V1 | B14: US-011 | C14: Inspect evidence and its provenance | D14: Consumer | E14: Evaluation | F14: Must Have | G14: As a Consumer, I want to open the evidence behind a parameter score, so that I can verify where the information came from. | H14: • Each evidence item shows source, source type, timestamp, freshness, verification state, methodology (where relevant), and document reference. • Evidence types are labelled: independently tested, expert-tested, manufacturer-published, marketplace-provided, community-reported, other authorized. • A manufacturer claim is never presented as an independent test. • A community complaint is never presented as a laboratory fact. | I14: • Positive: click a parameter; linked evidence opens with all provenance fields. • Negative: manufacturer spec sheet is not shown with the "independently tested" label. • Edge: evidence document later withdrawn; item marked as such and evaluation flagged for review. • Security: private evidence is hidden from users without permission. | J14: Draft
A15: V1 | B15: US-015 | C15: View community insights | D15: Consumer | E15: Community | F15: Must Have | G15: As a Consumer, I want a summary of community feedback, so that I can see recurring issues and positive experiences without reading every review. | H15: • Shows sentiment, recurring issues, positive experiences, and usage context. • Shown separately from the objective evaluation. • AI summaries are labelled and traceable to underlying feedback. • Feedback history is retained. | I15: • Positive: product with many reviews shows top recurring issues. • Negative: product with too few reviews shows a "not enough feedback" state. • Edge: contradictory feedback is shown as mixed, not averaged away. • Verify community data does not change the deterministic evaluation score. | J15: Draft
... A57: V3 | B57: US-053 | C57: Add a new domain evaluation model (restaurants, hotels, services) | D57: Admin | E57: Admin | F57: Could Have | G57: As an Admin, I want to add evaluation models for new domains (for example Restaurant v1, Hotel v1) on the shared entity platform, so that Review Master expands beyond products. | H57: • A new domain reuses shared identity, evidence, feedback, expert, confidence, comparison, recommendation, notification, and AI infrastructure. • Only domain parameters, normalization, evidence requirements, scoring rules, and recommendation constraints are new. • No redesign of the core platform is required. | I57: • Positive: configure a Restaurant v1 model; an entity can be evaluated end to end. • Verify product categories are unaffected by the new domain. • Edge: domain-specific evidence requirement differs; engine enforces it. | J57: Clarification Required
